gramexlayout/__init__.py
gramexlayout-0.2.1.dist-info/LICENSE.txt
gramexlayout-0.2.1.dist-info/METADATA
gramexlayout-0.2.1.dist-info/WHEEL
gramexlayout-0.2.1.dist-info/top_level.txt
gramexlayout-0.2.1.dist-info/RECORD
