Metadata-Version: 2.1
Name: gramexlayout
Version: 0.2.1
Summary: Layout algorithms for visualizations
Home-page: https://github.com/gramener/gramexlayout
Author: S Anand
Author-email: s.anand@gramener.com
License: MIT
Project-URL: Documentation, https://github.com/gramener/gramexlayout/
Project-URL: Source, https://github.com/gramener/gramexlayout/
Project-URL: Tracker, https://github.com/gramener/gramexlayout/issues
Platform: UNKNOWN
Classifier: Development Status :: 4 - Beta
Classifier: Intended Audience :: Developers
Classifier: License :: OSI Approved :: MIT License
Classifier: Operating System :: OS Independent
Classifier: Programming Language :: Python :: 3
Classifier: Programming Language :: Python :: 3.6
Classifier: Programming Language :: Python :: 3.7
Classifier: Programming Language :: Python :: 3.8
Classifier: Programming Language :: Python :: 3.9
Classifier: Topic :: Software Development
Classifier: Topic :: Software Development :: Libraries :: Python Modules
License-File: LICENSE.txt
Requires-Dist: pandas
